Workbook

Sheet À lire
A1: djoli | B1: Reconquête des clients sans commande depuis plus de 30 jours
A2: FICTIF : données inventées pour illustrer la méthode. Aucun nom, chiffre ou date ne vient de Djoli.
A4: Ce que contient ce classeur
A5: Clients inactifs | B5: Les 30 clients (fictifs) sans commande de produits frais depuis plus de 30 jours, avec leur rythme habituel, leur valeur et le groupe dans lequel ils tombent.
A6: Plan de relance | B6: Pour chaque client : priorité, canal, dates des 4 contacts, premier message déjà personnalisé, et colonnes de suivi à remplir par le commercial.
A7: Messages types | B7: Les messages de la séquence (jour 0, appel, jour 7 par raison, jour 14) et les questions d'appel.
A8: Suivi | B8: Les indicateurs qui se calculent seuls dès que le plan de relance est rempli.
A9: Paramètres | B9: La date de référence et les seuils : les changer met à jour les jours sans commande et les dates.
A11: Comment on trie
A12: Décroché | B12: Commandait au moins tous les 10 jours et son silence dépasse 3 fois son rythme habituel. Priorité de la relance.
A13: Incident non soldé | B13: Une réclamation (produit refusé, retard, erreur) dans les 15 jours avant l'arrêt. On règle l'incident avant toute offre.
A14: Impayé en cours | B14: Un encours reste dû. Pas de relance commerciale : le dossier passe d'abord au recouvrement.
A15: Rythme lent / occasionnel | B15: Commande tous les 14 jours ou plus : un mois sans commande peut être normal. Message léger, pas de pression.
A16: Perdu probable (> 90 j) | B16: Plus de 90 jours sans commande. On cherche surtout à comprendre pourquoi, l'offre vient ensuite.
A18: Comment on priorise
A19: P1 | B19: Valeur habituelle d'au moins 1,5 M FCFA par mois, ou incident sur un client d'au moins 500 000 FCFA par mois. Visite ou appel du responsable commercial, dans les 48 h.
A20: P2 | B20: Valeur habituelle d'au moins 600 000 FCFA par mois, ou incident. Appel du commercial qui suit le client.
A21: P3 | B21: Le reste. Message WhatsApp du commercial, depuis son numéro (pas d'envoi groupé).
A23: Ce qui ne part jamais sans accord | B23: Chaque message avant son envoi ; toute offre de retour, remise, livraison offerte ou prix bloqué (décision de la direction de Djoli) ; tout étalement d'une dette. Une condition accordée à un client ne se cite jamais à un autre.
A24: Valeur habituelle par mois | B24: Panier moyen × 30 / nombre de jours entre deux commandes. C'est ce que le client achetait en rythme normal, pas une promesse de chiffre retrouvé.

Sheet Paramètres
A1: djoli | B1: Paramètres
A2: FICTIF : données inventées pour illustrer la méthode. Aucun nom, chiffre ou date ne vient de Djoli.
A5: Date de référence | B5: 46316 | C5: Date à laquelle on compte les jours sans commande
A6: Seuil d'inactivité (jours) | B6: 30 | C6: En dessous, le client n'entre pas dans la relance
A7: Seuil « décroché » (silence / rythme) | B7: 3 | C7: Silence au moins 3 fois plus long que le rythme habituel
A8: Seuil « perdu probable » (jours) | B8: 90
A9: Seuil P1 (valeur par mois, FCFA) | B9: 1500000
A10: Seuil P2 (valeur par mois, FCFA) | B10: 600000
A11: Alerte précoce (silence / rythme) | B11: 1.5 | C11: À mettre en place ensuite : signaler un client dès 1,5 fois son rythme
A12: Date de départ de la campagne (J0) | B12: 46317 | C12: Jour 0 des clients P1 ; P2 à J0+1, P3 à J0+4

Sheet Clients inactifs
A1: djoli | B1: Clients sans commande de produits frais depuis plus de 30 jours
A2: FICTIF : données inventées pour illustrer la méthode. Aucun nom, chiffre ou date ne vient de Djoli.
A3: Trié par priorité puis par valeur habituelle. Les jours sans commande se recalculent depuis la date de référence (onglet Paramètres).
A5: ID | B5: Établissement | C5: Type | D5: Commune | E5: Contact | F5: Commercial | G5: Client depuis | H5: Dernière commande | I5: Jours sans commande | J5: Rythme habituel (jours) | K5: Silence / rythme | L5: Commandes sur les 90 j avant l'arrêt | M5: Panier moyen | N5: Valeur habituelle par mois | O5: CA 12 mois | P5: Produits habituels | Q5: Dernière réclamation | R5: Objet de la réclamation | S5: Encours dû | T5: Raison supposée (à confirmer) | U5: Famille de raison | V5: Groupe | W5: Priorité | X5: Canal du premier contact
A6: CLI-011 | B6: Hôtel Ivoire Palm (cuisine) | C6: Hôtel-restaurant | D6: Port-Bouët | E6: M. Kra, chef de cuisine | F6: Aïcha | G6: 45830 | H6: 46282 | I6: =Paramètres!$B$5-H6 | J6: 3 | K6: =ROUND(I6/J6,1) | L6: 29 | M6: 520000 | N6: 5200000 | O6: 59430000 | P6: Fruits, salade, tomate, herbes | S6: 0 | T6: Retour au marché ou autre fournisseur | U6: Concurrence / marché | V6: Décroché | W6: P1 | X6: Visite ou appel du responsable commercial
A7: CLI-001 | B7: Hôtel Lagune Bleue (restaurant) | C7: Hôtel-restaurant | D7: Marcory Zone 4 | E7: Mme Bamba, intendante | F7: Aïcha | G7: 46070 | H7: 46278 | I7: =Paramètres!$B$5-H7 | J7: 4 | K7: =ROUND(I7/J7,1) | L7: 18 | M7: 410000 | N7: 3075000 | O7: 21045000 | P7: Tomate 1er choix, salade, poivron | Q7: 46272 | R7: Tomates abîmées à la livraison | S7: 0 | T7: Qualité / fraîcheur | U7: Qualité | V7: Incident non soldé | W7: P1 | X7: Visite ou appel du responsable commercial
A8: CLI-006 | B8: Le Grill du Plateau | C8: Restaurant | D8: Plateau | E8: M. Diallo, chef | F8: Aïcha | G8: 45952 | H8: 46283 | I8: =Paramètres!$B$5-H8 | J8: 3 | K8: =ROUND(I8/J8,1) | L8: 29 | M8: 230000 | N8: 2300000 | O8: 23815000 | P8: Poivron, oignon, piment, citron vert | S8: 0 | T8: Nouvel acheteur en cuisine | U8: Changement d'interlocuteur | V8: Décroché | W8: P1 | X8: Visite ou appel du responsable commercial
A9: CLI-004 | B9: Résidence Les Flamboyants | C9: Hôtel-restaurant | D9: Cocody Riviera 3 | E9: M. Ouattara, chef | F9: Aïcha | G9: 45932 | H9: 46264 | I9: =Paramètres!$B$5-H9 | J9: 4 | K9: =ROUND(I9/J9,1) | L9: 18 | M9: 295000 | N9: 2212000 | O9: 22405000 | P9: Carotte, haricot vert, pomme de terre | Q9: 46255 | R9: Livraison arrivée après le service | S9: 0 | T9: Livraison en retard | U9: Service (livraison, erreur) | V9: Incident non soldé | W9: P1 | X9: Visite ou appel du responsable commercial
A10: CLI-002 | B10: Le Patio d'Angré | C10: Restaurant | D10: Cocody Angré | E10: M. Koffi, gérant | F10: Serge | G10: 45872 | H10: 46272 | I10: =Paramètres!$B$5-H10 | J10: 3 | K10: =ROUND(I10/J10,1) | L10: 24 | M10: 185000 | N10: 1850000 | O10: 19710000 | P10: Oignon, tomate, piment, citron | S10: 0 | T10: Retour au marché ou autre fournisseur | U10: Concurrence / marché | V10: Décroché | W10: P1 | X10: Visite ou appel du responsable commercial
A11: CLI-009 | B11: Fast Food Mixte 225 | C11: Restauration rapide | D11: Cocody II Plateaux | E11: Mme Coulibaly, gérante | F11: Serge | G11: 45837 | H11: 46280 | I11: =Paramètres!$B$5-H11 | J11: 4 | K11: =ROUND(I11/J11,1) | L11: 22 | M11: 98000 | N11: 735000 | O11: 8325000 | P11: Salade, tomate, oignon, frites fraîches | Q11: 46268 | R11: Salade fanée, refusée | S11: 0 | T11: Qualité / fraîcheur | U11: Qualité | V11: Incident non soldé | W11: P1 | X11: Visite ou appel du responsable commercial
A12: CLI-018 | B12: Restaurant Chez Fanta | C12: Restaurant | D12: Adjamé | E12: Mme Fofana, propriétaire | F12: Serge | G12: 46016 | H12: 46279 | I12: =Paramètres!$B$5-H12 | J12: 4 | K12: =ROUND(I12/J12,1) | L12: 17 | M12: 88000 | N12: 660000 | O12: 5550000 | P12: Oignon, tomate, piment, ail | Q12: 46275 | R12: Erreur dans la commande (produit manquant) | S12: 0 | T12: Erreur de commande | U12: Service (livraison, erreur) | V12: Incident non soldé | W12: P1 | X12: Visite ou appel du responsable commercial
A13: CLI-023 | B13: Cafétéria Clinique Les Lauriers | C13: Cantine | D13: Cocody Danga | E13: Mme Yapi, intendante | F13: Serge | G13: 45761 | H13: 46270 | I13: =Paramètres!$B$5-H13 | J13: 7 | K13: =ROUND(I13/J13,1) | L13: 11 | M13: 135000 | N13: 579000 | O13: 6595000 | P13: Légumes soupe, carotte, pomme de terre | Q13: 46262 | R13: Livraison incomplète | S13: 0 | T13: Livraison incomplète | U13: Service (livraison, erreur) | V13: Incident non soldé | W13: P1 | X13: Visite ou appel du responsable commercial
A14: CLI-015 | B14: Le Comptoir Gourmand | C14: Restaurant | D14: Marcory Biétry | E14: Mme Dosso, cheffe | F14: Aïcha | G14: 45802 | H14: 46285 | I14: =Paramètres!$B$5-H14 | J14: 4 | K14: =ROUND(I14/J14,1) | L14: 19 | M14: 175000 | N14: 1312000 | O14: 15600000 | P14: Herbes, citron, avocat, tomate cerise | S14: 0 | T14: Nouvel acheteur en cuisine | U14: Changement d'interlocuteur | V14: Décroché | W14: P2 | X14: Appel du commercial
A15: CLI-028 | B15: Le Jardin de Cocody | C15: Restaurant | D15: Cocody Ambassades | E15: Mme Brou, gérante | F15: Aïcha | G15: 45952 | H15: 46277 | I15: =Paramètres!$B$5-H15 | J15: 5 | K15: =ROUND(I15/J15,1) | L15: 17 | M15: 205000 | N15: 1230000 | O15: 11365000 | P15: Salade, herbes, légumes du jardin | S15: 0 | T15: Qualité / calibre irrégulier | U15: Qualité | V15: Décroché | W15: P2 | X15: Appel du commercial
A16: CLI-014 | B16: Cantine Entreprise Zone Industrielle | C16: Cantine | D16: Yopougon ZI | E16: M. Sylla, responsable achats | F16: Serge | G16: 45893 | H16: 46276 | I16: =Paramètres!$B$5-H16 | J16: 7 | K16: =ROUND(I16/J16,1) | L16: 12 | M16: 275000 | N16: 1179000 | O16: 12590000 | P16: Riz local, tomate, oignon, chou | S16: 0 | T16: Appel d'offres perdu / autre prestataire | U16: Concurrence / marché | V16: Décroché | W16: P2 | X16: Appel du commercial
A17: CLI-019 | B17: Le Bistrot du Golf | C17: Restaurant | D17: Cocody Riviera Golf | E17: M. Assi, gérant | F17: Aïcha | G17: 45772 | H17: 46274 | I17: =Paramètres!$B$5-H17 | J17: 5 | K17: =ROUND(I17/J17,1) | L17: 14 | M17: 190000 | N17: 1140000 | O17: 13635000 | P17: Salade, tomate, champignons, herbes | S17: 0 | T17: Prix jugé trop haut | U17: Prix | V17: Décroché | W17: P2 | X17: Appel du commercial
A18: CLI-025 | B18: Hôtel Résidence Akwaba (restaurant) | C18: Hôtel-restaurant | D18: Grand-Bassam | E18: M. Ahoussou, chef | F18: Aïcha | G18: 45805 | H18: 46258 | I18: =Paramètres!$B$5-H18 | J18: 7 | K18: =ROUND(I18/J18,1) | L18: 10 | M18: 260000 | N18: 1114000 | O18: 11745000 | P18: Fruits, légumes, poisson-légumes | S18: 0 | T18: Livraison hors zone jugée chère | U18: Prix | V18: Décroché | W18: P2 | X18: Appel du commercial
A19: CLI-005 | B19: Cantine Groupe Scolaire Les Palmiers | C19: Cantine | D19: Abobo | E19: Mme Touré, économe | F19: Serge | G19: 46090 | H19: 46255 | I19: =Paramètres!$B$5-H19 | J19: 7 | K19: =ROUND(I19/J19,1) | L19: 11 | M19: 240000 | N19: 1029000 | O19: 5255000 | P19: Riz local, oignon, tomate, chou | S19: 0 | T19: Changement de prestataire de restauration | U19: Concurrence / marché | V19: Décroché | W19: P2 | X19: Appel du commercial
A20: CLI-024 | B20: Burger & Co Angré | C20: Restauration rapide | D20: Cocody Angré | E20: M. Traoré, gérant | F20: Serge | G20: 46020 | H20: 46284 | I20: =Paramètres!$B$5-H20 | J20: 4 | K20: =ROUND(I20/J20,1) | L20: 17 | M20: 120000 | N20: 900000 | O20: 7540000 | P20: Salade, tomate, oignon rouge | S20: 0 | T20: Prix jugé trop haut | U20: Prix | V20: Décroché | W20: P2 | X20: Appel du commercial
A21: CLI-012 | B21: Restaurant Le Lagunaire | C21: Restaurant | D21: Cocody Blockhauss | E21: Mme Aka, gérante | F21: Serge | G21: 45836 | H21: 46244 | I21: =Paramètres!$B$5-H21 | J21: 6 | K21: =ROUND(I21/J21,1) | L21: 13 | M21: 140000 | N21: 700000 | O21: 7250000 | P21: Poisson-légumes, attiéké-garniture | S21: 0 | T21: Fermeture temporaire (travaux) | U21: Activité du client | V21: Décroché | W21: P2 | X21: Appel du commercial
A22: CLI-010 | B22: La Table de Treichville | C22: Restaurant | D22: Treichville | E22: M. N'Guessan, propriétaire | F22: Aïcha | G22: 46108 | H22: 46277 | I22: =Paramètres!$B$5-H22 | J22: 5 | K22: =ROUND(I22/J22,1) | L22: 16 | M22: 115000 | N22: 690000 | O22: 3595000 | P22: Tomate, oignon, poisson-légumes | S22: 0 | T22: Prix jugé trop haut | U22: Prix | V22: Décroché | W22: P2 | X22: Appel du commercial
A23: CLI-016 | B23: Traiteur Les Délices d'Anoumabo | C23: Traiteur | D23: Marcory Anoumabo | E23: Mme Kouakou, gérante | F23: Mariam | G23: 46091 | H23: 46261 | I23: =Paramètres!$B$5-H23 | J23: 10 | K23: =ROUND(I23/J23,1) | L23: 8 | M23: 210000 | N23: 630000 | O23: 3215000 | P23: Tomate, oignon, poivron, carotte | S23: 0 | T23: Activité saisonnière (événements) | U23: Activité du client | V23: Décroché | W23: P2 | X23: Appel du commercial
A24: CLI-022 | B24: Restaurant Le Vieux Port | C24: Restaurant | D24: Port-Bouët | E24: M. Tanoh, chef | F24: Aïcha | G24: 45974 | H24: 46221 | I24: =Paramètres!$B$5-H24 | J24: 5 | K24: =ROUND(I24/J24,1) | L24: 14 | M24: 160000 | N24: 960000 | O24: 7860000 | P24: Poisson-légumes, tomate, citron | S24: 0 | T24: Retour au marché ou autre fournisseur | U24: Concurrence / marché | V24: Perdu probable (> 90 j) | W24: P3 | X24: WhatsApp du commercial
A25: CLI-029 | B25: Traiteur Mariages & Baptêmes Awa | C25: Traiteur | D25: Yopougon Maroc | E25: Mme Diabaté, gérante | F25: Serge | G25: 45950 | H25: 46267 | I25: =Paramètres!$B$5-H25 | J25: 21 | K25: =ROUND(I25/J25,1) | L25: 4 | M25: 380000 | N25: 543000 | O25: 5335000 | P25: Tomate, oignon, poivron en gros | S25: 0 | T25: Rythme normal (occasionnel) | U25: Activité du client | V25: Rythme lent / occasionnel | W25: P3 | X25: WhatsApp du commercial
... A35: CLI-030 | B35: Maquis Le Plaisir | C35: Maquis | D35: Treichville | E35: M. Zadi, gérant | F35: Mariam | G35: 45739 | H35: 46253 | I35: =Paramètres!$B$5-H35 | J35: 5 | K35: =ROUND(I35/J35,1) | L35: 17 | M35: 58000 | N35: 348000 | O35: 4070000 | P35: Piment, gombo, oignon | S35: 18000 | T35: Difficulté de paiement | U35: Paiement | V35: Impayé en cours | W35: À part | X35: Recouvrement d'abord, puis appel
B37: Total (30 clients) | N37: =SUM(N6:N35) | O37: =SUM(O6:O35) | S37: =SUM(S6:S35)

Sheet Plan de relance
A1: djoli | B1: Plan de relance : un client, une ligne
A2: FICTIF : données inventées pour illustrer la méthode. Aucun nom, chiffre ou date ne vient de Djoli.
A3: Les dates se calculent depuis la date de départ (Paramètres). Rien ne part tant que la colonne « Validé par » est vide.
A5: ID | B5: Établissement | C5: Commercial | D5: Priorité | E5: Groupe | F5: Canal | G5: Jour 0 | H5: Jour 3 (appel) | I5: Jour 7 | J5: Jour 14 | K5: Message du jour 0 (brouillon, à valider) | L5: Validé par | M5: Statut | N5: Réponse du client (ses mots) | O5: Raison réelle | P5: Offre proposée (si validée) | Q5: Recommande le | R5: Montant 1re commande retour
A6: CLI-011 | B6: Hôtel Ivoire Palm (cuisine) | C6: Aïcha | D6: P1 | E6: Décroché | F6: Visite ou appel du responsable commercial | G6: =Paramètres!$B$12+0 | H6: =G6+3 | I6: =G6+7 | J6: =G6+14 | K6: Bonjour M. Kra, c'est Aïcha de Djoli. Ça fait 4 semaines qu'on ne vous a pas livré au Hôtel Ivoire Palm (cuisine), je voulais simplement prendre de vos nouvelles. Est-ce que quelque chose ne vous a pas convenu de notre côté ? Même deux mots m'aident vraiment. | M6: À valider
A7: CLI-001 | B7: Hôtel Lagune Bleue (restaurant) | C7: Aïcha | D7: P1 | E7: Incident non soldé | F7: Visite ou appel du responsable commercial | G7: =Paramètres!$B$12+0 | H7: =G7+3 | I7: =G7+7 | J7: =G7+14 | K7: Bonjour Mme Bamba, c'est Aïcha de Djoli. Je reviens vers vous au sujet de la livraison du 07/09 (tomates abîmées à la livraison). Je voulais savoir si cela a été réglé correctement pour vous, et sinon le reprendre avec vous. Est-ce que je peux vous appeler cinq minutes cette semaine ? | M7: À valider
A8: CLI-006 | B8: Le Grill du Plateau | C8: Aïcha | D8: P1 | E8: Décroché | F8: Visite ou appel du responsable commercial | G8: =Paramètres!$B$12+0 | H8: =G8+3 | I8: =G8+7 | J8: =G8+14 | K8: Bonjour M. Diallo, c'est Aïcha de Djoli. Ça fait 4 semaines qu'on ne vous a pas livré au Le Grill du Plateau, je voulais simplement prendre de vos nouvelles. Est-ce que quelque chose ne vous a pas convenu de notre côté ? Même deux mots m'aident vraiment. | M8: À valider
A9: CLI-004 | B9: Résidence Les Flamboyants | C9: Aïcha | D9: P1 | E9: Incident non soldé | F9: Visite ou appel du responsable commercial | G9: =Paramètres!$B$12+0 | H9: =G9+3 | I9: =G9+7 | J9: =G9+14 | K9: Bonjour M. Ouattara, c'est Aïcha de Djoli. Je reviens vers vous au sujet de la livraison du 21/08 (livraison arrivée après le service). Je voulais savoir si cela a été réglé correctement pour vous, et sinon le reprendre avec vous. Est-ce que je peux vous appeler cinq minutes cette semaine ? | M9: À valider
A10: CLI-002 | B10: Le Patio d'Angré | C10: Serge | D10: P1 | E10: Décroché | F10: Visite ou appel du responsable commercial | G10: =Paramètres!$B$12+0 | H10: =G10+3 | I10: =G10+7 | J10: =G10+14 | K10: Bonjour M. Koffi, c'est Serge de Djoli. Ça fait 6 semaines qu'on ne vous a pas livré au Le Patio d'Angré, je voulais simplement prendre de vos nouvelles. Est-ce que quelque chose ne vous a pas convenu de notre côté ? Même deux mots m'aident vraiment. | M10: À valider
A11: CLI-009 | B11: Fast Food Mixte 225 | C11: Serge | D11: P1 | E11: Incident non soldé | F11: Visite ou appel du responsable commercial | G11: =Paramètres!$B$12+0 | H11: =G11+3 | I11: =G11+7 | J11: =G11+14 | K11: Bonjour Mme Coulibaly, c'est Serge de Djoli. Je reviens vers vous au sujet de la livraison du 03/09 (salade fanée, refusée). Je voulais savoir si cela a été réglé correctement pour vous, et sinon le reprendre avec vous. Est-ce que je peux vous appeler cinq minutes cette semaine ? | M11: À valider
A12: CLI-018 | B12: Restaurant Chez Fanta | C12: Serge | D12: P1 | E12: Incident non soldé | F12: Visite ou appel du responsable commercial | G12: =Paramètres!$B$12+0 | H12: =G12+3 | I12: =G12+7 | J12: =G12+14 | K12: Bonjour Mme Fofana, c'est Serge de Djoli. Je reviens vers vous au sujet de la livraison du 10/09 (erreur dans la commande (produit manquant)). Je voulais savoir si cela a été réglé correctement pour vous, et sinon le reprendre avec vous. Est-ce que je peux vous appeler cinq minutes cette semaine ? | M12: À valider
A13: CLI-023 | B13: Cafétéria Clinique Les Lauriers | C13: Serge | D13: P1 | E13: Incident non soldé | F13: Visite ou appel du responsable commercial | G13: =Paramètres!$B$12+0 | H13: =G13+3 | I13: =G13+7 | J13: =G13+14 | K13: Bonjour Mme Yapi, c'est Serge de Djoli. Je reviens vers vous au sujet de la livraison du 28/08 (livraison incomplète). Je voulais savoir si cela a été réglé correctement pour vous, et sinon le reprendre avec vous. Est-ce que je peux vous appeler cinq minutes cette semaine ? | M13: À valider
A14: CLI-015 | B14: Le Comptoir Gourmand | C14: Aïcha | D14: P2 | E14: Décroché | F14: Appel du commercial | G14: =Paramètres!$B$12+1 | H14: =G14+3 | I14: =G14+7 | J14: =G14+14 | K14: Bonjour Mme Dosso, c'est Aïcha de Djoli. Ça fait 4 semaines qu'on ne vous a pas livré au Le Comptoir Gourmand, je voulais simplement prendre de vos nouvelles. Est-ce que quelque chose ne vous a pas convenu de notre côté ? Même deux mots m'aident vraiment. | M14: À valider
A15: CLI-028 | B15: Le Jardin de Cocody | C15: Aïcha | D15: P2 | E15: Décroché | F15: Appel du commercial | G15: =Paramètres!$B$12+1 | H15: =G15+3 | I15: =G15+7 | J15: =G15+14 | K15: Bonjour Mme Brou, c'est Aïcha de Djoli. Ça fait 5 semaines qu'on ne vous a pas livré au Le Jardin de Cocody, je voulais simplement prendre de vos nouvelles. Est-ce que quelque chose ne vous a pas convenu de notre côté ? Même deux mots m'aident vraiment. | M15: À valider
A16: CLI-014 | B16: Cantine Entreprise Zone Industrielle | C16: Serge | D16: P2 | E16: Décroché | F16: Appel du commercial | G16: =Paramètres!$B$12+1 | H16: =G16+3 | I16: =G16+7 | J16: =G16+14 | K16: Bonjour M. Sylla, c'est Serge de Djoli. Ça fait 5 semaines qu'on ne vous a pas livré au Cantine Entreprise Zone Industrielle, je voulais simplement prendre de vos nouvelles. Est-ce que quelque chose ne vous a pas convenu de notre côté ? Même deux mots m'aident vraiment. | M16: À valider
A17: CLI-019 | B17: Le Bistrot du Golf | C17: Aïcha | D17: P2 | E17: Décroché | F17: Appel du commercial | G17: =Paramètres!$B$12+1 | H17: =G17+3 | I17: =G17+7 | J17: =G17+14 | K17: Bonjour M. Assi, c'est Aïcha de Djoli. Ça fait 6 semaines qu'on ne vous a pas livré au Le Bistrot du Golf, je voulais simplement prendre de vos nouvelles. Est-ce que quelque chose ne vous a pas convenu de notre côté ? Même deux mots m'aident vraiment. | M17: À valider
A18: CLI-025 | B18: Hôtel Résidence Akwaba (restaurant) | C18: Aïcha | D18: P2 | E18: Décroché | F18: Appel du commercial | G18: =Paramètres!$B$12+1 | H18: =G18+3 | I18: =G18+7 | J18: =G18+14 | K18: Bonjour M. Ahoussou, c'est Aïcha de Djoli. Ça fait 8 semaines qu'on ne vous a pas livré au Hôtel Résidence Akwaba (restaurant), je voulais simplement prendre de vos nouvelles. Est-ce que quelque chose ne vous a pas convenu de notre côté ? Même deux mots m'aident vraiment. | M18: À valider
A19: CLI-005 | B19: Cantine Groupe Scolaire Les Palmiers | C19: Serge | D19: P2 | E19: Décroché | F19: Appel du commercial | G19: =Paramètres!$B$12+1 | H19: =G19+3 | I19: =G19+7 | J19: =G19+14 | K19: Bonjour Mme Touré, c'est Serge de Djoli. Ça fait 8 semaines qu'on ne vous a pas livré au Cantine Groupe Scolaire Les Palmiers, je voulais simplement prendre de vos nouvelles. Est-ce que quelque chose ne vous a pas convenu de notre côté ? Même deux mots m'aident vraiment. | M19: À valider
A20: CLI-024 | B20: Burger & Co Angré | C20: Serge | D20: P2 | E20: Décroché | F20: Appel du commercial | G20: =Paramètres!$B$12+1 | H20: =G20+3 | I20: =G20+7 | J20: =G20+14 | K20: Bonjour M. Traoré, c'est Serge de Djoli. Ça fait 4 semaines qu'on ne vous a pas livré au Burger & Co Angré, je voulais simplement prendre de vos nouvelles. Est-ce que quelque chose ne vous a pas convenu de notre côté ? Même deux mots m'aident vraiment. | M20: À valider
A21: CLI-012 | B21: Restaurant Le Lagunaire | C21: Serge | D21: P2 | E21: Décroché | F21: Appel du commercial | G21: =Paramètres!$B$12+1 | H21: =G21+3 | I21: =G21+7 | J21: =G21+14 | K21: Bonjour Mme Aka, c'est Serge de Djoli. Ça fait 10 semaines qu'on ne vous a pas livré au Restaurant Le Lagunaire, je voulais simplement prendre de vos nouvelles. Est-ce que quelque chose ne vous a pas convenu de notre côté ? Même deux mots m'aident vraiment. | M21: À valider
A22: CLI-010 | B22: La Table de Treichville | C22: Aïcha | D22: P2 | E22: Décroché | F22: Appel du commercial | G22: =Paramètres!$B$12+1 | H22: =G22+3 | I22: =G22+7 | J22: =G22+14 | K22: Bonjour M. N'Guessan, c'est Aïcha de Djoli. Ça fait 5 semaines qu'on ne vous a pas livré au La Table de Treichville, je voulais simplement prendre de vos nouvelles. Est-ce que quelque chose ne vous a pas convenu de notre côté ? Même deux mots m'aident vraiment. | M22: À valider
A23: CLI-016 | B23: Traiteur Les Délices d'Anoumabo | C23: Mariam | D23: P2 | E23: Décroché | F23: Appel du commercial | G23: =Paramètres!$B$12+1 | H23: =G23+3 | I23: =G23+7 | J23: =G23+14 | K23: Bonjour Mme Kouakou, c'est Mariam de Djoli. Ça fait 7 semaines qu'on ne vous a pas livré au Traiteur Les Délices d'Anoumabo, je voulais simplement prendre de vos nouvelles. Est-ce que quelque chose ne vous a pas convenu de notre côté ? Même deux mots m'aident vraiment. | M23: À valider
A24: CLI-022 | B24: Restaurant Le Vieux Port | C24: Aïcha | D24: P3 | E24: Perdu probable (> 90 j) | F24: WhatsApp du commercial | G24: =Paramètres!$B$12+4 | H24: =G24+3 | I24: =G24+7 | J24: =G24+14 | K24: Bonjour M. Tanoh, c'est Aïcha de Djoli. Ça fait un moment qu'on ne s'est pas parlé. Si le Restaurant Le Vieux Port a changé d'organisation ou de fournisseur, aucun souci : j'aimerais juste comprendre ce qui vous a fait partir, pour nous améliorer. Vous auriez deux minutes pour me répondre ? | M24: À valider
A25: CLI-029 | B25: Traiteur Mariages & Baptêmes Awa | C25: Serge | D25: P3 | E25: Rythme lent / occasionnel | F25: WhatsApp du commercial | G25: =Paramètres!$B$12+4 | H25: =G25+3 | I25: =G25+7 | J25: =G25+14 | K25: Bonjour Mme Diabaté, c'est Serge de Djoli. J'espère que tout va bien au Traiteur Mariages & Baptêmes Awa. Vous avez un événement ou un gros service en vue ces prochaines semaines ? Je peux vous préparer la liste habituelle à l'avance pour que vous n'ayez qu'à valider. | M25: À valider
A26: CLI-027 | B26: Restaurant Saveurs du Nord | C26: Mariam | D26: P3 | E26: Décroché | F26: WhatsApp du commercial | G26: =Paramètres!$B$12+4 | H26: =G26+3 | I26: =G26+7 | J26: =G26+14 | K26: Bonjour M. Cissé, c'est Mariam de Djoli. Ça fait 4 semaines qu'on ne vous a pas livré au Restaurant Saveurs du Nord, je voulais simplement prendre de vos nouvelles. Est-ce que quelque chose ne vous a pas convenu de notre côté ? Même deux mots m'aident vraiment. | M26: À valider
A27: CLI-003 | B27: Maquis Chez Tantie Rose | C27: Mariam | D27: P3 | E27: Décroché | F27: WhatsApp du commercial | G27: =Paramètres!$B$12+4 | H27: =G27+3 | I27: =G27+7 | J27: =G27+14 | K27: Bonjour Mme Gnagne, c'est Mariam de Djoli. Ça fait 5 semaines qu'on ne vous a pas livré au Maquis Chez Tantie Rose, je voulais simplement prendre de vos nouvelles. Est-ce que quelque chose ne vous a pas convenu de notre côté ? Même deux mots m'aident vraiment. | M27: À valider
A28: CLI-017 | B28: Maquis La Paillote | C28: Mariam | D28: P3 | E28: Perdu probable (> 90 j) | F28: WhatsApp du commercial | G28: =Paramètres!$B$12+4 | H28: =G28+3 | I28: =G28+7 | J28: =G28+14 | K28: Bonjour M. Gbané, c'est Mariam de Djoli. Ça fait un moment qu'on ne s'est pas parlé. Si le Maquis La Paillote a changé d'organisation ou de fournisseur, aucun souci : j'aimerais juste comprendre ce qui vous a fait partir, pour nous améliorer. Vous auriez deux minutes pour me répondre ? | M28: À valider
A29: CLI-008 | B29: Maquis Le Baobab | C29: Mariam | D29: P3 | E29: Décroché | F29: WhatsApp du commercial | G29: =Paramètres!$B$12+4 | H29: =G29+3 | I29: =G29+7 | J29: =G29+14 | K29: Bonjour M. Yao, c'est Mariam de Djoli. Ça fait 5 semaines qu'on ne vous a pas livré au Maquis Le Baobab, je voulais simplement prendre de vos nouvelles. Est-ce que quelque chose ne vous a pas convenu de notre côté ? Même deux mots m'aident vraiment. | M29: À valider
A30: CLI-021 | B30: Maquis Le Carrefour | C30: Mariam | D30: P3 | E30: Décroché | F30: WhatsApp du commercial | G30: =Paramètres!$B$12+4 | H30: =G30+3 | I30: =G30+7 | J30: =G30+14 | K30: Bonjour M. Bakayoko, c'est Mariam de Djoli. Ça fait 4 semaines qu'on ne vous a pas livré au Maquis Le Carrefour, je voulais simplement prendre de vos nouvelles. Est-ce que quelque chose ne vous a pas convenu de notre côté ? Même deux mots m'aident vraiment. | M30: À valider
A31: CLI-020 | B31: Pâtisserie-Salon Le Fromager | C31: Serge | D31: P3 | E31: Rythme lent / occasionnel | F31: WhatsApp du commercial | G31: =Paramètres!$B$12+4 | H31: =G31+3 | I31: =G31+7 | J31: =G31+14 | K31: Bonjour Mme Ehui, c'est Serge de Djoli. J'espère que tout va bien au Pâtisserie-Salon Le Fromager. Vous avez un événement ou un gros service en vue ces prochaines semaines ? Je peux vous préparer la liste habituelle à l'avance pour que vous n'ayez qu'à valider. | M31: À valider
A32: CLI-013 | B32: Allocodrome Riviera (stand 12) | C32: Mariam | D32: P3 | E32: Décroché | F32: WhatsApp du commercial | G32: =Paramètres!$B$12+4 | H32: =G32+3 | I32: =G32+7 | J32: =G32+14 | K32: Bonjour M. Konan, c'est Mariam de Djoli. Ça fait 6 semaines qu'on ne vous a pas livré au Allocodrome Riviera (stand 12), je voulais simplement prendre de vos nouvelles. Est-ce que quelque chose ne vous a pas convenu de notre côté ? Même deux mots m'aident vraiment. | M32: À valider
A33: CLI-026 | B33: Maquis Chez Ablo | C33: Mariam | D33: P3 | E33: Décroché | F33: WhatsApp du commercial | G33: =Paramètres!$B$12+4 | H33: =G33+3 | I33: =G33+7 | J33: =G33+14 | K33: Bonjour M. Ablo, c'est Mariam de Djoli. Ça fait 7 semaines qu'on ne vous a pas livré au Maquis Chez Ablo, je voulais simplement prendre de vos nouvelles. Est-ce que quelque chose ne vous a pas convenu de notre côté ? Même deux mots m'aident vraiment. | M33: À valider
A34: CLI-007 | B34: Saveurs de Bingerville | C34: Mariam | D34: À part | E34: Impayé en cours | F34: Recouvrement d'abord, puis appel | G34: =Paramètres!$B$12+7 | H34: =G34+3 | I34: =G34+7 | J34: =G34+14 | K34: ⟦Pas de message commercial : encours de 145 000 FCFA à traiter d'abord par le recouvrement⟧ | M34: À valider
A35: CLI-030 | B35: Maquis Le Plaisir | C35: Mariam | D35: À part | E35: Impayé en cours | F35: Recouvrement d'abord, puis appel | G35: =Paramètres!$B$12+7 | H35: =G35+3 | I35: =G35+7 | J35: =G35+14 | K35: ⟦Pas de message commercial : encours de 18 000 FCFA à traiter d'abord par le recouvrement⟧ | M35: À valider

Sheet Messages types
A1: djoli | B1: Messages de la séquence (brouillons, rien ne part sans accord)
A2: FICTIF : données inventées pour illustrer la méthode. Aucun nom, chiffre ou date ne vient de Djoli.
A3: Variables entre accolades ; ⟦…⟧ = à décider ou à confirmer par Djoli avant tout envoi.
A5: Quand | B5: Canal | C5: Cas | D5: Message ou question
A6: Jour 0 | B6: WhatsApp du commercial | C6: Décroché | D6: Bonjour {civ}, c'est {com} de Djoli. Ça fait {sem} semaines qu'on ne vous a pas livré au {etab}, je voulais simplement prendre de vos nouvelles. Est-ce que quelque chose ne vous a pas convenu de notre côté ? Même deux mots m'aident vraiment.
A7: Jour 0 | B7: WhatsApp du commercial | C7: Incident non soldé | D7: Bonjour {civ}, c'est {com} de Djoli. Je reviens vers vous au sujet de la livraison du {date_inc} ({inc}). Je voulais savoir si cela a été réglé correctement pour vous, et sinon le reprendre avec vous. Est-ce que je peux vous appeler cinq minutes cette semaine ?
A8: Jour 0 | B8: WhatsApp du commercial | C8: Rythme lent / occasionnel | D8: Bonjour {civ}, c'est {com} de Djoli. J'espère que tout va bien au {etab}. Vous avez un événement ou un gros service en vue ces prochaines semaines ? Je peux vous préparer la liste habituelle à l'avance pour que vous n'ayez qu'à valider.
A9: Jour 0 | B9: WhatsApp du commercial | C9: Perdu probable | D9: Bonjour {civ}, c'est {com} de Djoli. Ça fait un moment qu'on ne s'est pas parlé. Si le {etab} a changé d'organisation ou de fournisseur, aucun souci : j'aimerais juste comprendre ce qui vous a fait partir, pour nous améliorer. Vous auriez deux minutes pour me répondre ?
A10: Jour 3 | B10: Appel (ou visite P1) | C10: Questions à poser | D10: Comment se passe l'activité en ce moment ? (fréquentation, saison, travaux)
A11: Jour 3 | B11: Appel (ou visite P1) | C11: Questions à poser | D11: Pour vos produits frais, vous passez par qui aujourd'hui ? (marché, autre plateforme, grossiste)
A12: Jour 3 | B12: Appel (ou visite P1) | C12: Questions à poser | D12: Qu'est-ce qui a fait que vous avez arrêté de commander chez nous ? (laisser parler, noter les mots exacts)
A13: Jour 3 | B13: Appel (ou visite P1) | C13: Questions à poser | D13: Qu'est-ce qu'il faudrait pour que vous repassiez une commande ?
A14: Jour 3 | B14: Appel (ou visite P1) | C14: Questions à poser | D14: Qui décide des achats en cuisine aujourd'hui ? (si nouvel acheteur : demander son contact)
A15: Jour 7 | B15: WhatsApp | C15: Raison : Prix | D15: {civ}, comme promis : votre panier habituel ({produits}) revient cette semaine à ⟦montant réel au prix du jour⟧ chez Djoli, livré et trié. Au marché, il faut compter le transport, le temps d'achat et la part jetée. Je vous fais une commande test sur ces produits pour comparer ?
A16: Jour 7 | B16: WhatsApp | C16: Raison : Concurrence / marché | D16: {civ}, je vous propose un essai simple : une commande test sur vos {produits}, livrée avant votre service, pour comparer avec ce que vous avez aujourd'hui. Vous me dites le jour qui vous arrange ?
... A23: Jour 14 | B23: WhatsApp | C23: Pas de réponse : clôture | D23: {civ}, je ne veux pas vous encombrer : je referme le sujet de mon côté. Si le moment change, un simple mot suffit et je reviens vers vous. Bonne continuation au {etab}.
A24: Toujours | C24: Arrêt immédiat | D24: Le client répond « non », « STOP » ou demande qu'on ne le contacte plus : on arrête et on note la raison. Un client parti chez un concurrent est rappelé dans 60 jours, pas avant.

Sheet Suivi
A1: djoli | B1: Suivi de la campagne
A2: FICTIF : données inventées pour illustrer la méthode. Aucun nom, chiffre ou date ne vient de Djoli.
A3: Se remplit seul à partir du plan de relance.
A5: Indicateur | B5: Valeur | D5: Note
A6: Clients dans la campagne | B6: =COUNTA('Plan de relance'!A6:A35)
A7: Messages validés | B7: =COUNTA('Plan de relance'!L6:L35) | D7: Colonne « Validé par » remplie
A8: Clients qui ont répondu | B8: =COUNTIF('Plan de relance'!M6:M35,"Répondu")+COUNTIF('Plan de relance'!M6:M35,"Rappel prévu")+COUNTIF('Plan de relance'!M6:M35,"Recommande")+COUNTIF('Plan de relance'!M6:M35,"Ne revient pas")
A9: Taux de réponse | B9: =IFERROR(B8/B6,0)
A10: Clients qui ont recommandé | B10: =COUNTIF('Plan de relance'!M6:M35,"Recommande")
A11: Taux de retour | B11: =IFERROR(B10/B6,0) | D11: Objectif : ⟦à fixer par Djoli⟧
A12: Montant des premières commandes retour | B12: =SUM('Plan de relance'!R6:R35)
A13: Valeur habituelle par mois des clients revenus | B13: =SUMIF('Plan de relance'!M6:M35,"Recommande",'Clients inactifs'!N6:N35) | D13: Ce que ces clients achetaient en rythme normal
A14: Valeur habituelle par mois en jeu (30 clients) | B14: =SUM('Clients inactifs'!N6:N35)
A17: Raisons réelles relevées (colonne O du plan)
A18: Famille de raison | B18: Supposée (départ) | C18: Confirmée
A19: Concurrence / marché | B19: =COUNTIF('Clients inactifs'!U6:U35,A19) | C19: =COUNTIF('Plan de relance'!O6:O35,A19)
A20: Prix | B20: =COUNTIF('Clients inactifs'!U6:U35,A20) | C20: =COUNTIF('Plan de relance'!O6:O35,A20)
A21: Qualité | B21: =COUNTIF('Clients inactifs'!U6:U35,A21) | C21: =COUNTIF('Plan de relance'!O6:O35,A21)
A22: Service (livraison, erreur) | B22: =COUNTIF('Clients inactifs'!U6:U35,A22) | C22: =COUNTIF('Plan de relance'!O6:O35,A22)
A23: Paiement | B23: =COUNTIF('Clients inactifs'!U6:U35,A23) | C23: =COUNTIF('Plan de relance'!O6:O35,A23)
A24: Changement d'interlocuteur | B24: =COUNTIF('Clients inactifs'!U6:U35,A24) | C24: =COUNTIF('Plan de relance'!O6:O35,A24)
A25: Activité du client | B25: =COUNTIF('Clients inactifs'!U6:U35,A25) | C25: =COUNTIF('Plan de relance'!O6:O35,A25)
A26: Autre | B26: =COUNTIF('Clients inactifs'!U6:U35,A26) | C26: =COUNTIF('Plan de relance'!O6:O35,A26)
A28: Si une même raison confirmée revient chez plus d'un client sur cinq, c'est un sujet d'offre ou d'opérations à remonter à la direction : la relance ne le réglera pas.
