Workbook

Sheet À lire
B1: 📈 Suivi des affaires de la force de vente
A2: Modèle prêt à remplir. Une ligne par affaire, une mise à jour après chaque contact.
B4: 🧭 Comment s'en servir
B5: 1️⃣ Onglet « Affaires » : une ligne par distributeur. Les 30 prospects de la liste sont déjà inscrits à l'étape « À contacter ».
B6: 2️⃣ Après chaque appel, visite ou message : changer l'étape (liste déroulante), noter le montant estimé de la première commande, la prochaine action et sa date.
B7: 3️⃣ La colonne « Alerte » s'allume toute seule : « En retard » si la date de la prochaine action est passée, « Sans suite prévue » si aucune action n'est notée.
B8: 4️⃣ Onglet « Synthèse » : nombre d'affaires et montants par étape et par commercial, mis à jour automatiquement.
B9: 5️⃣ Onglet « Paramètres » : la liste des étapes et la probabilité de signature de chacune. Ces probabilités sont des hypothèses de départ, à ajuster après trois mois de données réelles.
B11: 🚦 Les étapes
B12: 📋 À contacter → 📞 Premier contact fait → 🤝 Rendez-vous obtenu → 🎁 Échantillons ou catalogue remis → 📄 Offre envoyée → 💬 Négociation → 🏆 Gagné (première commande) / ❌ Perdu.
B14: ⚠️ Règles de la maison à rappeler à l'équipe
B15: Aucun prix, aucune remise et aucun délai de paiement ne sont promis sans l'accord de la direction commerciale. Les montants saisis sont des estimations du commercial, pas des engagements.
B16: Les colonnes « Montant estimé » sont vides au départ : elles se remplissent après le premier rendez-vous.

Sheet Affaires
A1: N° | B1: 🏢 Distributeur | C1: 🌍 Pays | D1: 🏷️ Type | E1: 🎯 Priorité | F1: 👤 Commercial | G1: 🚦 Étape | H1: 💰 Montant estimé 1re commande (F CFA) | I1: 📈 Probabilité | J1: ⚖️ Montant pondéré (F CFA) | K1: 📅 Dernier contact | L1: ➡️ Prochaine action | M1: ⏰ Date prochaine action | N1: 🔔 Alerte | O1: 📝 Notes
A2: 1 | B2: Groupe Prosuma (Cash Center, Sococé, Hayat, Bon Prix…) | C2: 🇨🇮 Côte d'Ivoire | D2: Chaîne de supermarchés et centrale d'achats | E2: Haute | G2: À contacter | I2: =IF(G2="","",IFERROR(VLOOKUP(G2,Paramètres!$A$2:$B$9,2,FALSE),"")) | J2: =IF(OR(H2="",I2=""),"",H2*I2) | N2: =IF(B2="","",IF(OR(G2="Gagné (première commande)",G2="Perdu"),"Clos",IF(M2="","Sans suite prévue",IF(M2<TODAY(),"En retard","À jour"))))
A3: 2 | B3: CDCI - Compagnie de Distribution de Côte d'Ivoire | C3: 🇨🇮 Côte d'Ivoire | D3: Chaîne de supermarchés et distribution | E3: Haute | G3: À contacter | I3: =IF(G3="","",IFERROR(VLOOKUP(G3,Paramètres!$A$2:$B$9,2,FALSE),"")) | J3: =IF(OR(H3="",I3=""),"",H3*I3) | N3: =IF(B3="","",IF(OR(G3="Gagné (première commande)",G3="Perdu"),"Clos",IF(M3="","Sans suite prévue",IF(M3<TODAY(),"En retard","À jour"))))
A4: 3 | B4: CFAO Retail (Carrefour, PlaYce) | C4: 🇨🇮 Côte d'Ivoire | D4: Hypermarchés et supermarchés | E4: Haute | G4: À contacter | I4: =IF(G4="","",IFERROR(VLOOKUP(G4,Paramètres!$A$2:$B$9,2,FALSE),"")) | J4: =IF(OR(H4="",I4=""),"",H4*I4) | N4: =IF(B4="","",IF(OR(G4="Gagné (première commande)",G4="Perdu"),"Clos",IF(M4="","Sans suite prévue",IF(M4<TODAY(),"En retard","À jour"))))
A5: 4 | B5: Copharmed (CFAO Healthcare) | C5: 🇨🇮 Côte d'Ivoire | D5: Grossiste répartiteur pharmaceutique | E5: Haute | G5: À contacter | I5: =IF(G5="","",IFERROR(VLOOKUP(G5,Paramètres!$A$2:$B$9,2,FALSE),"")) | J5: =IF(OR(H5="",I5=""),"",H5*I5) | N5: =IF(B5="","",IF(OR(G5="Gagné (première commande)",G5="Perdu"),"Clos",IF(M5="","Sans suite prévue",IF(M5<TODAY(),"En retard","À jour"))))
A6: 5 | B6: UbiPharm Côte d'Ivoire | C6: 🇨🇮 Côte d'Ivoire | D6: Grossiste répartiteur pharmaceutique | E6: Haute | G6: À contacter | I6: =IF(G6="","",IFERROR(VLOOKUP(G6,Paramètres!$A$2:$B$9,2,FALSE),"")) | J6: =IF(OR(H6="",I6=""),"",H6*I6) | N6: =IF(B6="","",IF(OR(G6="Gagné (première commande)",G6="Perdu"),"Clos",IF(M6="","Sans suite prévue",IF(M6<TODAY(),"En retard","À jour"))))
A7: 6 | B7: DPCI - Distribution Pharmaceutique de Côte d'Ivoire | C7: 🇨🇮 Côte d'Ivoire | D7: Grossiste répartiteur pharmaceutique | E7: Haute | G7: À contacter | I7: =IF(G7="","",IFERROR(VLOOKUP(G7,Paramètres!$A$2:$B$9,2,FALSE),"")) | J7: =IF(OR(H7="",I7=""),"",H7*I7) | N7: =IF(B7="","",IF(OR(G7="Gagné (première commande)",G7="Perdu"),"Clos",IF(M7="","Sans suite prévue",IF(M7<TODAY(),"En retard","À jour"))))
A8: 7 | B8: Jumia Côte d'Ivoire | C8: 🇨🇮 Côte d'Ivoire | D8: Plateforme de vente en ligne | E8: Haute | G8: À contacter | I8: =IF(G8="","",IFERROR(VLOOKUP(G8,Paramètres!$A$2:$B$9,2,FALSE),"")) | J8: =IF(OR(H8="",I8=""),"",H8*I8) | N8: =IF(B8="","",IF(OR(G8="Gagné (première commande)",G8="Perdu"),"Clos",IF(M8="","Sans suite prévue",IF(M8<TODAY(),"En retard","À jour"))))
A9: 8 | B9: Ivoire Center | C9: 🇨🇮 Côte d'Ivoire | D9: Chaîne de supermarchés | E9: Moyenne | G9: À contacter | I9: =IF(G9="","",IFERROR(VLOOKUP(G9,Paramètres!$A$2:$B$9,2,FALSE),"")) | J9: =IF(OR(H9="",I9=""),"",H9*I9) | N9: =IF(B9="","",IF(OR(G9="Gagné (première commande)",G9="Perdu"),"Clos",IF(M9="","Sans suite prévue",IF(M9<TODAY(),"En retard","À jour"))))
A10: 9 | B10: King Cash | C10: 🇨🇮 Côte d'Ivoire | D10: Chaîne de supermarchés et cash | E10: Moyenne | G10: À contacter | I10: =IF(G10="","",IFERROR(VLOOKUP(G10,Paramètres!$A$2:$B$9,2,FALSE),"")) | J10: =IF(OR(H10="",I10=""),"",H10*I10) | N10: =IF(B10="","",IF(OR(G10="Gagné (première commande)",G10="Perdu"),"Clos",IF(M10="","Sans suite prévue",IF(M10<TODAY(),"En retard","À jour"))))
A11: 10 | B11: Tedis Pharma CI | C11: 🇨🇮 Côte d'Ivoire | D11: Grossiste répartiteur pharmaceutique | E11: Moyenne | G11: À contacter | I11: =IF(G11="","",IFERROR(VLOOKUP(G11,Paramètres!$A$2:$B$9,2,FALSE),"")) | J11: =IF(OR(H11="",I11=""),"",H11*I11) | N11: =IF(B11="","",IF(OR(G11="Gagné (première commande)",G11="Perdu"),"Clos",IF(M11="","Sans suite prévue",IF(M11<TODAY(),"En retard","À jour"))))
A12: 11 | B12: Glovo Côte d'Ivoire | C12: 🇨🇮 Côte d'Ivoire | D12: Livraison à la demande (supermarchés et boutiques) | E12: Moyenne | G12: À contacter | I12: =IF(G12="","",IFERROR(VLOOKUP(G12,Paramètres!$A$2:$B$9,2,FALSE),"")) | J12: =IF(OR(H12="",I12=""),"",H12*I12) | N12: =IF(B12="","",IF(OR(G12="Gagné (première commande)",G12="Perdu"),"Clos",IF(M12="","Sans suite prévue",IF(M12<TODAY(),"En retard","À jour"))))
A13: 12 | B13: Fabellashop | C13: 🇨🇮 Côte d'Ivoire | D13: Parapharmacie et beauté en ligne | E13: Moyenne | G13: À contacter | I13: =IF(G13="","",IFERROR(VLOOKUP(G13,Paramètres!$A$2:$B$9,2,FALSE),"")) | J13: =IF(OR(H13="",I13=""),"",H13*I13) | N13: =IF(B13="","",IF(OR(G13="Gagné (première commande)",G13="Perdu"),"Clos",IF(M13="","Sans suite prévue",IF(M13<TODAY(),"En retard","À jour"))))
... A31: 30 | B31: Laborex Guinée (CFAO Healthcare) | C31: 🇬🇳 Guinée | D31: Grossiste répartiteur pharmaceutique | E31: Moyenne | G31: À contacter | I31: =IF(G31="","",IFERROR(VLOOKUP(G31,Paramètres!$A$2:$B$9,2,FALSE),"")) | J31: =IF(OR(H31="",I31=""),"",H31*I31) | N31: =IF(B31="","",IF(OR(G31="Gagné (première commande)",G31="Perdu"),"Clos",IF(M31="","Sans suite prévue",IF(M31<TODAY(),"En retard","À jour"))))
A32: 31 | I32: =IF(G32="","",IFERROR(VLOOKUP(G32,Paramètres!$A$2:$B$9,2,FALSE),"")) | J32: =IF(OR(H32="",I32=""),"",H32*I32) | N32: =IF(B32="","",IF(OR(G32="Gagné (première commande)",G32="Perdu"),"Clos",IF(M32="","Sans suite prévue",IF(M32<TODAY(),"En retard","À jour"))))
A33: 32 | I33: =IF(G33="","",IFERROR(VLOOKUP(G33,Paramètres!$A$2:$B$9,2,FALSE),"")) | J33: =IF(OR(H33="",I33=""),"",H33*I33) | N33: =IF(B33="","",IF(OR(G33="Gagné (première commande)",G33="Perdu"),"Clos",IF(M33="","Sans suite prévue",IF(M33<TODAY(),"En retard","À jour"))))
A34: 33 | I34: =IF(G34="","",IFERROR(VLOOKUP(G34,Paramètres!$A$2:$B$9,2,FALSE),"")) | J34: =IF(OR(H34="",I34=""),"",H34*I34) | N34: =IF(B34="","",IF(OR(G34="Gagné (première commande)",G34="Perdu"),"Clos",IF(M34="","Sans suite prévue",IF(M34<TODAY(),"En retard","À jour"))))
A35: 34 | I35: =IF(G35="","",IFERROR(VLOOKUP(G35,Paramètres!$A$2:$B$9,2,FALSE),"")) | J35: =IF(OR(H35="",I35=""),"",H35*I35) | N35: =IF(B35="","",IF(OR(G35="Gagné (première commande)",G35="Perdu"),"Clos",IF(M35="","Sans suite prévue",IF(M35<TODAY(),"En retard","À jour"))))
A36: 35 | I36: =IF(G36="","",IFERROR(VLOOKUP(G36,Paramètres!$A$2:$B$9,2,FALSE),"")) | J36: =IF(OR(H36="",I36=""),"",H36*I36) | N36: =IF(B36="","",IF(OR(G36="Gagné (première commande)",G36="Perdu"),"Clos",IF(M36="","Sans suite prévue",IF(M36<TODAY(),"En retard","À jour"))))
A37: 36 | I37: =IF(G37="","",IFERROR(VLOOKUP(G37,Paramètres!$A$2:$B$9,2,FALSE),"")) | J37: =IF(OR(H37="",I37=""),"",H37*I37) | N37: =IF(B37="","",IF(OR(G37="Gagné (première commande)",G37="Perdu"),"Clos",IF(M37="","Sans suite prévue",IF(M37<TODAY(),"En retard","À jour"))))
A38: 37 | I38: =IF(G38="","",IFERROR(VLOOKUP(G38,Paramètres!$A$2:$B$9,2,FALSE),"")) | J38: =IF(OR(H38="",I38=""),"",H38*I38) | N38: =IF(B38="","",IF(OR(G38="Gagné (première commande)",G38="Perdu"),"Clos",IF(M38="","Sans suite prévue",IF(M38<TODAY(),"En retard","À jour"))))
A39: 38 | I39: =IF(G39="","",IFERROR(VLOOKUP(G39,Paramètres!$A$2:$B$9,2,FALSE),"")) | J39: =IF(OR(H39="",I39=""),"",H39*I39) | N39: =IF(B39="","",IF(OR(G39="Gagné (première commande)",G39="Perdu"),"Clos",IF(M39="","Sans suite prévue",IF(M39<TODAY(),"En retard","À jour"))))
A40: 39 | I40: =IF(G40="","",IFERROR(VLOOKUP(G40,Paramètres!$A$2:$B$9,2,FALSE),"")) | J40: =IF(OR(H40="",I40=""),"",H40*I40) | N40: =IF(B40="","",IF(OR(G40="Gagné (première commande)",G40="Perdu"),"Clos",IF(M40="","Sans suite prévue",IF(M40<TODAY(),"En retard","À jour"))))
A41: 40 | I41: =IF(G41="","",IFERROR(VLOOKUP(G41,Paramètres!$A$2:$B$9,2,FALSE),"")) | J41: =IF(OR(H41="",I41=""),"",H41*I41) | N41: =IF(B41="","",IF(OR(G41="Gagné (première commande)",G41="Perdu"),"Clos",IF(M41="","Sans suite prévue",IF(M41<TODAY(),"En retard","À jour"))))
A42: 41 | I42: =IF(G42="","",IFERROR(VLOOKUP(G42,Paramètres!$A$2:$B$9,2,FALSE),"")) | J42: =IF(OR(H42="",I42=""),"",H42*I42) | N42: =IF(B42="","",IF(OR(G42="Gagné (première commande)",G42="Perdu"),"Clos",IF(M42="","Sans suite prévue",IF(M42<TODAY(),"En retard","À jour"))))
A43: 42 | I43: =IF(G43="","",IFERROR(VLOOKUP(G43,Paramètres!$A$2:$B$9,2,FALSE),"")) | J43: =IF(OR(H43="",I43=""),"",H43*I43) | N43: =IF(B43="","",IF(OR(G43="Gagné (première commande)",G43="Perdu"),"Clos",IF(M43="","Sans suite prévue",IF(M43<TODAY(),"En retard","À jour"))))
... A61: 60 | I61: =IF(G61="","",IFERROR(VLOOKUP(G61,Paramètres!$A$2:$B$9,2,FALSE),"")) | J61: =IF(OR(H61="",I61=""),"",H61*I61) | N61: =IF(B61="","",IF(OR(G61="Gagné (première commande)",G61="Perdu"),"Clos",IF(M61="","Sans suite prévue",IF(M61<TODAY(),"En retard","À jour"))))

Sheet Synthèse
B1: 📊 Synthèse du pipeline
A2: Calculée automatiquement à partir de l'onglet « Affaires ».
A4: Étape | B4: Nombre d'affaires | C4: Montant estimé (F CFA) | D4: Montant pondéré (F CFA) | E4: Part des affaires
A5: À contacter | B5: =COUNTIF(Affaires!$G$2:$G$61,A5) | C5: =SUMIF(Affaires!$G$2:$G$61,A5,Affaires!$H$2:$H$61) | D5: =SUMIF(Affaires!$G$2:$G$61,A5,Affaires!$J$2:$J$61) | E5: =IFERROR(B5/$B$13,0)
A6: Premier contact fait | B6: =COUNTIF(Affaires!$G$2:$G$61,A6) | C6: =SUMIF(Affaires!$G$2:$G$61,A6,Affaires!$H$2:$H$61) | D6: =SUMIF(Affaires!$G$2:$G$61,A6,Affaires!$J$2:$J$61) | E6: =IFERROR(B6/$B$13,0)
A7: Rendez-vous obtenu | B7: =COUNTIF(Affaires!$G$2:$G$61,A7) | C7: =SUMIF(Affaires!$G$2:$G$61,A7,Affaires!$H$2:$H$61) | D7: =SUMIF(Affaires!$G$2:$G$61,A7,Affaires!$J$2:$J$61) | E7: =IFERROR(B7/$B$13,0)
A8: Échantillons ou catalogue remis | B8: =COUNTIF(Affaires!$G$2:$G$61,A8) | C8: =SUMIF(Affaires!$G$2:$G$61,A8,Affaires!$H$2:$H$61) | D8: =SUMIF(Affaires!$G$2:$G$61,A8,Affaires!$J$2:$J$61) | E8: =IFERROR(B8/$B$13,0)
A9: Offre envoyée | B9: =COUNTIF(Affaires!$G$2:$G$61,A9) | C9: =SUMIF(Affaires!$G$2:$G$61,A9,Affaires!$H$2:$H$61) | D9: =SUMIF(Affaires!$G$2:$G$61,A9,Affaires!$J$2:$J$61) | E9: =IFERROR(B9/$B$13,0)
A10: Négociation | B10: =COUNTIF(Affaires!$G$2:$G$61,A10) | C10: =SUMIF(Affaires!$G$2:$G$61,A10,Affaires!$H$2:$H$61) | D10: =SUMIF(Affaires!$G$2:$G$61,A10,Affaires!$J$2:$J$61) | E10: =IFERROR(B10/$B$13,0)
A11: Gagné (première commande) | B11: =COUNTIF(Affaires!$G$2:$G$61,A11) | C11: =SUMIF(Affaires!$G$2:$G$61,A11,Affaires!$H$2:$H$61) | D11: =SUMIF(Affaires!$G$2:$G$61,A11,Affaires!$J$2:$J$61) | E11: =IFERROR(B11/$B$13,0)
A12: Perdu | B12: =COUNTIF(Affaires!$G$2:$G$61,A12) | C12: =SUMIF(Affaires!$G$2:$G$61,A12,Affaires!$H$2:$H$61) | D12: =SUMIF(Affaires!$G$2:$G$61,A12,Affaires!$J$2:$J$61) | E12: =IFERROR(B12/$B$13,0)
A13: Total | B13: =SUM(B5:B12) | C13: =SUM(C5:C12) | D13: =SUM(D5:D12) | E13: =IF(B13>0,1,0)
A15: 🔔 Alertes
A16: Alerte | B16: Nombre
A17: En retard | B17: =COUNTIF(Affaires!$N$2:$N$61,A17)
A18: Sans suite prévue | B18: =COUNTIF(Affaires!$N$2:$N$61,A18)
A19: À jour | B19: =COUNTIF(Affaires!$N$2:$N$61,A19)
A20: Clos | B20: =COUNTIF(Affaires!$N$2:$N$61,A20)
A22: 👥 Par commercial
A23: Commercial | B23: Affaires ouvertes | C23: Montant pondéré (F CFA) | D23: En retard
A24: =Paramètres!A12 | B24: =COUNTIFS(Affaires!$F$2:$F$61,A24,Affaires!$N$2:$N$61,"<>Clos") | C24: =SUMIF(Affaires!$F$2:$F$61,A24,Affaires!$J$2:$J$61) | D24: =COUNTIFS(Affaires!$F$2:$F$61,A24,Affaires!$N$2:$N$61,"En retard")
A25: =Paramètres!A13 | B25: =COUNTIFS(Affaires!$F$2:$F$61,A25,Affaires!$N$2:$N$61,"<>Clos") | C25: =SUMIF(Affaires!$F$2:$F$61,A25,Affaires!$J$2:$J$61) | D25: =COUNTIFS(Affaires!$F$2:$F$61,A25,Affaires!$N$2:$N$61,"En retard")
A26: =Paramètres!A14 | B26: =COUNTIFS(Affaires!$F$2:$F$61,A26,Affaires!$N$2:$N$61,"<>Clos") | C26: =SUMIF(Affaires!$F$2:$F$61,A26,Affaires!$J$2:$J$61) | D26: =COUNTIFS(Affaires!$F$2:$F$61,A26,Affaires!$N$2:$N$61,"En retard")
A27: =Paramètres!A15 | B27: =COUNTIFS(Affaires!$F$2:$F$61,A27,Affaires!$N$2:$N$61,"<>Clos") | C27: =SUMIF(Affaires!$F$2:$F$61,A27,Affaires!$J$2:$J$61) | D27: =COUNTIFS(Affaires!$F$2:$F$61,A27,Affaires!$N$2:$N$61,"En retard")
A28: =Paramètres!A16 | B28: =COUNTIFS(Affaires!$F$2:$F$61,A28,Affaires!$N$2:$N$61,"<>Clos") | C28: =SUMIF(Affaires!$F$2:$F$61,A28,Affaires!$J$2:$J$61) | D28: =COUNTIFS(Affaires!$F$2:$F$61,A28,Affaires!$N$2:$N$61,"En retard")

Sheet Paramètres
A1: 🚦 Étape | B1: Probabilité de signature | C1: Remarque
A2: À contacter | B2: 0
A3: Premier contact fait | B3: 0.05 | C3: hypothèse de départ, à ajuster
A4: Rendez-vous obtenu | B4: 0.15 | C4: hypothèse de départ, à ajuster
A5: Échantillons ou catalogue remis | B5: 0.25 | C5: hypothèse de départ, à ajuster
A6: Offre envoyée | B6: 0.4 | C6: hypothèse de départ, à ajuster
A7: Négociation | B7: 0.6 | C7: hypothèse de départ, à ajuster
A8: Gagné (première commande) | B8: 1
A9: Perdu | B9: 0
A11: Commerciaux (à renseigner)
A12: Commercial 1
A13: Commercial 2
A14: Commercial 3
A15: Commercial 4
A16: Commercial 5
A18: Date du jour | B18: =TODAY()
