Workbook

Sheet À lire
B2: TAJ PLAST · Cartographie des cibles commerciales
B3: Abidjan et intérieur · relevé du 27/10/2026 · préparé par Kouassi, Expert commercial (Yelema)
B5: Ce que contient ce classeur
B6: • Synthèse : le nombre de cibles par catégorie, vérifiées et à vérifier, et les priorités A. Les chiffres se recalculent quand on modifie l'onglet Cibles.
B7: • Cibles : une ligne par entreprise, avec la commune, les produits Taj Plast à pousser, le contact public, l'angle d'approche, la source et le statut. Filtres actifs en ligne d'en-tête.
B8: • Zones d'Adjamé : les pôles de grossistes à couvrir à pied, faute de liste nominative fiable.
B9: • Méthode et limites : comment la liste a été construite et ce qu'il reste à faire.
B11: Comment lire la colonne Certitude
B12: • Vérifié : l'entreprise existe, confirmée par une source officielle, un site actif ou la presse récente.
B13: • À vérifier : nom trouvé sur une seule fiche d'annuaire ou dans une source ancienne. Un appel ou un passage avant toute approche.
B15: Priorité
B16: • A : volume ou effet de réseau important, signal d'achat daté. À ouvrir dans les deux semaines.
... B20: Aucun nom n'a été inventé : chaque ligne renvoie à sa source. Les contacts sont des numéros publics (standard, annuaire). Aucun contact n'a été pris au nom de Taj Plast.

Sheet Synthèse
A1: Synthèse de la cartographie
A2: Se recalcule à partir de l'onglet Cibles.
A4: Catégorie | B4: Cibles | C4: Vérifiées | D4: À vérifier | E4: Priorité A | F4: Abidjan | G4: Intérieur ou national | H4: Revendeurs ouverts
A5: Quincailleries & matériaux | B5: =COUNTIF(Cibles!$C:$C,A5) | C5: =COUNTIFS(Cibles!$C:$C,A5,Cibles!$K:$K,"Vérifié") | D5: =COUNTIFS(Cibles!$C:$C,A5,Cibles!$K:$K,"À vérifier") | E5: =COUNTIFS(Cibles!$C:$C,A5,Cibles!$L:$L,"A") | F5: =COUNTIFS(Cibles!$C:$C,A5,Cibles!$D:$D,"Abidjan") | G5: =B5-F5 | H5: =COUNTIFS(Cibles!$C:$C,A5,Cibles!$M:$M,"Revendeur ouvert")
A6: Grossistes Adjamé & marchés | B6: =COUNTIF(Cibles!$C:$C,A6) | C6: =COUNTIFS(Cibles!$C:$C,A6,Cibles!$K:$K,"Vérifié") | D6: =COUNTIFS(Cibles!$C:$C,A6,Cibles!$K:$K,"À vérifier") | E6: =COUNTIFS(Cibles!$C:$C,A6,Cibles!$L:$L,"A") | F6: =COUNTIFS(Cibles!$C:$C,A6,Cibles!$D:$D,"Abidjan") | G6: =B6-F6 | H6: =COUNTIFS(Cibles!$C:$C,A6,Cibles!$M:$M,"Revendeur ouvert")
A7: Supermarchés & distribution | B7: =COUNTIF(Cibles!$C:$C,A7) | C7: =COUNTIFS(Cibles!$C:$C,A7,Cibles!$K:$K,"Vérifié") | D7: =COUNTIFS(Cibles!$C:$C,A7,Cibles!$K:$K,"À vérifier") | E7: =COUNTIFS(Cibles!$C:$C,A7,Cibles!$L:$L,"A") | F7: =COUNTIFS(Cibles!$C:$C,A7,Cibles!$D:$D,"Abidjan") | G7: =B7-F7 | H7: =COUNTIFS(Cibles!$C:$C,A7,Cibles!$M:$M,"Revendeur ouvert")
A8: BTP & promoteurs (cuves, fosses) | B8: =COUNTIF(Cibles!$C:$C,A8) | C8: =COUNTIFS(Cibles!$C:$C,A8,Cibles!$K:$K,"Vérifié") | D8: =COUNTIFS(Cibles!$C:$C,A8,Cibles!$K:$K,"À vérifier") | E8: =COUNTIFS(Cibles!$C:$C,A8,Cibles!$L:$L,"A") | F8: =COUNTIFS(Cibles!$C:$C,A8,Cibles!$D:$D,"Abidjan") | G8: =B8-F8 | H8: =COUNTIFS(Cibles!$C:$C,A8,Cibles!$M:$M,"Revendeur ouvert")
A9: Écoles & universités privées | B9: =COUNTIF(Cibles!$C:$C,A9) | C9: =COUNTIFS(Cibles!$C:$C,A9,Cibles!$K:$K,"Vérifié") | D9: =COUNTIFS(Cibles!$C:$C,A9,Cibles!$K:$K,"À vérifier") | E9: =COUNTIFS(Cibles!$C:$C,A9,Cibles!$L:$L,"A") | F9: =COUNTIFS(Cibles!$C:$C,A9,Cibles!$D:$D,"Abidjan") | G9: =B9-F9 | H9: =COUNTIFS(Cibles!$C:$C,A9,Cibles!$M:$M,"Revendeur ouvert")
A10: Mairies & acheteurs publics | B10: =COUNTIF(Cibles!$C:$C,A10) | C10: =COUNTIFS(Cibles!$C:$C,A10,Cibles!$K:$K,"Vérifié") | D10: =COUNTIFS(Cibles!$C:$C,A10,Cibles!$K:$K,"À vérifier") | E10: =COUNTIFS(Cibles!$C:$C,A10,Cibles!$L:$L,"A") | F10: =COUNTIFS(Cibles!$C:$C,A10,Cibles!$D:$D,"Abidjan") | G10: =B10-F10 | H10: =COUNTIFS(Cibles!$C:$C,A10,Cibles!$M:$M,"Revendeur ouvert")
A11: Total | B11: =SUM(B5:B10) | C11: =SUM(C5:C10) | D11: =SUM(D5:D10) | E11: =SUM(E5:E10) | F11: =SUM(F5:F10) | G11: =SUM(G5:G10) | H11: =SUM(H5:H10)
A13: Par où commencer demain
A14: 1. Centrales qui démultiplient : Prosuma (une centrale pour plus de 100 magasins), CDCI, Carrefour (CFAO), Auchan.
A15: 2. Réseaux de quincailleries : DMD (environ 29 succursales), Bernabé, SIMC CI. Ce sont eux qui vendent cuves et fosses au détail.
A16: 3. Chantiers datés : Addoha, SNGI, Kaydan, Folourgo, AH Africa, Contractor CI (liste du ministère de la Construction, version du 31/08/2026).
A17: 4. Achat public : s'inscrire sur marchespublics.ci. Kolia, Zuénoula et Bettié ont acheté des chaises ou des tables-bancs par appel d'offres en 2025-2026.
A18: 5. Adjamé : tournée à pied sur les pôles de l'onglet Zones, avec catalogue et échantillons.

Sheet Cibles
A1: N° | B1: Nom | C1: Catégorie | D1: Zone | E1: Commune / ville | F1: Type | G1: Produits Taj Plast à pousser | H1: Contact public | I1: Signal ou angle d'approche | J1: Source | K1: Certitude | L1: Priorité | M1: Statut de prospection | N1: Prochaine action | O1: Responsable
A2: 1 | B2: Bernabé Côte d'Ivoire SA (groupe Yeshi) | C2: Quincailleries & matériaux | D2: Abidjan + intérieur | E2: Treichville, bd de Marseille km 4 ; agence San-Pédro | F2: Grand négociant quincaillerie et matériaux | G2: Cuves, fosses septiques, puits d'infiltration, tube orange | H2: 27 21 21 20 20 ; San-Pédro 27 34 71 14 49 | I2: Réseau multi-sites : un référencement couvre Abidjan et San-Pédro | J2: https://www.goafricaonline.com/ci/annuaire/quincailleries | K2: Vérifié | L2: A | M2: À contacter
A3: 2 | B3: Technibat | C3: Quincailleries & matériaux | D3: Abidjan | E3: Treichville, bd de Marseille (même adresse que Bernabé) | F3: Quincaillerie, sanitaire, jardin | G3: Cuves, fosses, poubelles, articles de jardin | H3: 27 21 21 20 20 | I3: Rayon sanitaire : fosses et cuves en complément | J3: https://www.goafricaonline.com/ci/annuaire/quincailleries | K3: À vérifier | L3: B | M3: À contacter
A4: 3 | B4: DMD SARL (Distribution de Marchandises Diverses) | C4: Quincailleries & matériaux | D4: Abidjan + intérieur | E4: Adjamé (6 succursales), Angré, Treichville, Marcory VGE ; Bouaké, Divo | F4: Grossiste-quincaillier, environ 29 succursales | G4: Cuves, fosses, tube orange, mobilier | H4: Adjamé 07 08 28 19 49 ; showroom VGE 07 77 77 63 83 | I4: Le plus grand réseau repéré : une seule centrale, des dizaines de points de vente | J4: https://www.goafricaonline.com/ci/573051-dmd-distributeur | K4: Vérifié | L4: A | M4: À contacter
A5: 4 | B5: SODIMAT (Société de Distribution de Matériaux) | C5: Quincailleries & matériaux | D5: Abidjan | E5: Treichville, bd de Marseille face au Palais des Sports | F5: Distributeur de matériaux | G5: Cuves, fosses, tube orange | H5: 27 21 25 31 41 | I5: Fiche d'annuaire seulement : appeler avant de visiter | J5: https://www.goafricaonline.com/ci/45537-sodimat-quincaillerie-abidjan-cote-ivoire | K5: À vérifier | L5: B | M5: À contacter
A6: 5 | B6: Mondial Cycles Nouvelle | C6: Quincailleries & matériaux | D6: Abidjan + intérieur | E6: Adjamé, Treichville, Yopougon, Bouaké, Daloa, Korhogo, San-Pédro, Man, Gagnoa, Divo, Soubré, Abengourou | F6: Revendeur multi-villes | G6: Articles de ménage, mobilier, cuves | H6: Bouaké 27 31 63 36 91 ; Daloa 27 32 78 33 75 ; Korhogo 27 36 86 35 67 | I6: Présent dans 12 villes : porte d'entrée vers l'intérieur. Activité exacte à confirmer | J6: https://universelleindustries.com/revendeurs-2 | K6: À vérifier | L6: A | M6: À contacter
A7: 6 | B7: SIMC CI | C7: Quincailleries & matériaux | D7: Abidjan | E7: Treichville, zone 3, rue des Carrossiers ; Riviera Faya | F7: Matériaux, plomberie, traitement de l'eau | G7: Cuves, fosses, puits d'infiltration | H7: 07 67 09 99 99 | I7: Spécialiste de l'eau : prescripteur naturel des cuves | J7: https://www.goafricaonline.com/ci/annuaire/materiaux-construction | K7: Vérifié | L7: A | M7: À contacter
A8: 7 | B8: BATI-ONE | C8: Quincailleries & matériaux | D8: Abidjan | E8: Cocody Riviera, route de Bingerville | F8: Quincaillerie | G8: Cuves, fosses (chantiers de Bingerville) | H8: 27 22 47 47 49 | I8: Sur l'axe des grands chantiers de Bingerville | J8: https://www.goafricaonline.com/ci/annuaire/quincailleries?p=2 | K8: À vérifier | L8: B | M8: À contacter
A9: 8 | B9: QGH (Quincaillerie Générale Hawaraa) | C9: Quincailleries & matériaux | D9: Abidjan | E9: Cocody Riviera Palmeraie | F9: Quincaillerie générale | G9: Cuves, fosses, poubelles | H9: 27 22 47 45 84 | I9: Quartier résidentiel en construction | J9: https://www.goafricaonline.com/ci/45402-qgh-quincaillerie-general-hawaraa-abidjan-cote-ivoire | K9: À vérifier | L9: C | M9: À contacter
A10: 9 | B10: Quincaillerie SOLID_BTP (« chez Mustapha ») | C10: Quincailleries & matériaux | D10: Intérieur | E10: Daloa | F10: Quincaillerie BTP | G10: Cuves, fosses, tube orange | H10: 07 77 24 25 77 | I10: Active en 2026 (mention Facebook de juin 2026) | J10: https://www.goafricaonline.com/ci/812566-quincaillerie-solid-btp | K10: Vérifié | L10: B | M10: À contacter
A11: 10 | B11: Quincaillerie du Centre | C11: Quincailleries & matériaux | D11: Intérieur | E11: Bouaké, Grand marché | F11: Quincaillerie, fournitures bâtiment | G11: Cuves, fosses, articles de ménage | H11: non relevé | I11: Grand marché de Bouaké : point de distribution du Centre | J11: https://www.goafricaonline.com/ci/646590-quincaillerie-centre-bouake-cote-ivoire | K11: À vérifier | L11: B | M11: À contacter
A12: 11 | B12: Quincaillerie Konaté Adja | C12: Quincailleries & matériaux | D12: Intérieur | E12: Bouaké, Grand marché | F12: Quincaillerie, matériaux | G12: Cuves, fosses | H12: non relevé | I12: À qualifier par téléphone | J12: https://annuaireci.com/entreprises/quincaillerie-konate-adja-abidjan-cote-divoire/ | K12: À vérifier | L12: C | M12: À contacter
A13: 12 | B13: GSD | C13: Quincailleries & matériaux | D13: Intérieur | E13: Yamoussoukro, Grand marché, Habitat | F13: Quincaillerie | G13: Cuves, fosses, mobilier | H13: 27 30 64 04 34 | I13: À qualifier par téléphone | J13: https://www.goafricaonline.com/ci/101704-gsd-quincaillerie-yamoussoukro-cote-ivoire | K13: À vérifier | L13: C | M13: À contacter
... A73: 72 | B73: Université internationale ICK (U2ICK) | C73: Écoles & universités privées | D73: Intérieur | E73: Bouaké | F73: Université privée | G73: Chaises, tables | H73: non relevé | I73: Rentrée académique couverte par Fraternité Matin | J73: https://www.fratmat.info/article/2638446/societe/enseignement-superieur-luniversite-internationale-ick-de-bouake-fait-sa-rentree-academique | K73: Vérifié | L73: B | M73: À contacter
A74: 73 | B74: HEC Abidjan | C74: Écoles & universités privées | D74: Abidjan | E74: Abidjan (commune à vérifier) | F74: École de commerce privée, fondée en 2001 | G74: Chaises, tables | H74: non relevé | J74: https://fede.education/en/ecoles/hec-abidjan | K74: À vérifier | L74: C | M74: À contacter
A75: 74 | B75: Enseignement catholique, archidiocèse de Bouaké | C75: Écoles & universités privées | D75: Intérieur | E75: Bouaké | F75: Réseau de collèges et écoles catholiques | G75: Chaises, tables, tables-bancs | H75: liste des établissements sur le site | I75: Un prescripteur pour plusieurs écoles | J75: https://archidiocesedebouake.org/services-diocesains/enseignement-catholique | K75: Vérifié | L75: B | M75: À contacter
A76: 75 | B76: Mairie de Koumassi (maire : Cissé Bacongo) | C76: Mairies & acheteurs publics | D76: Abidjan | E76: Koumassi | F76: Commune, siège de l'usine Taj Plast | G76: Chaises, tables, poubelles, bacs | H76: non relevé | I76: Commune de l'usine : argument « emploi local ». Réélu en 2023 | J76: https://lhorizoninfo.com/1er-conseil-municipal-a-koumassi-le-triomphe-du-maire-sortant-cisse-bacongo/ | K76: Vérifié | L76: A | M76: À contacter
A77: 76 | B77: Mairie de Cocody (maire : Jean-Marc Yacé) | C77: Mairies & acheteurs publics | D77: Abidjan | E77: Cocody | F77: Commune | G77: Chaises, tables, poubelles | H77: site mairiecocody.com | I77: Élu le 05/10/2023 | J77: https://mairiecocody.com/detail_news.php?etat=0&news=108 | K77: Vérifié | L77: B | M77: À contacter
A78: 77 | B78: Mairie de Yopougon (maire : Adama Bictogo) | C78: Mairies & acheteurs publics | D78: Abidjan | E78: Yopougon | F78: Commune la plus peuplée d'Abidjan | G78: Chaises, tables, poubelles | H78: non relevé | I78: Mandat 2023-2028 | J78: https://news.abidjan.net/articles/724692/adama-bictogo-prend-officiellement-fonction-a-la-tete-de-la-mairie-de-yopougon | K78: Vérifié | L78: A | M78: À contacter
A79: 78 | B79: Mairie d'Abobo (maire : Kandia Camara) | C79: Mairies & acheteurs publics | D79: Abidjan | E79: Abobo | F79: Commune | G79: Chaises, tables, poubelles | H79: non relevé | I79: Élue en 2023 | J79: https://www.fratmat.info/article/233479/politique/abobo-kandia-camara-elue-maire-avec-985-des-suffrages | K79: Vérifié | L79: B | M79: À contacter
A80: 79 | B80: Mairie de Marcory (maire : Raoul Aby) | C80: Mairies & acheteurs publics | D80: Abidjan | E80: Marcory | F80: Commune voisine de Koumassi | G80: Chaises, tables, poubelles | H80: site marcory.ci | I80: Réélu en 2023 | J80: https://www.marcory.ci/ | K80: Vérifié | L80: B | M80: À contacter
A81: 80 | B81: Mairie de Treichville (maire : François Albert Amichia) | C81: Mairies & acheteurs publics | D81: Abidjan | E81: Treichville | F81: Commune | G81: Chaises, tables, poubelles | H81: non relevé | I81: Réélu en 2023 | J81: https://www.fratmat.info/article/233706/politique/eacutelections-municipales/treichville-amichia-francois-reelu-a-la-tete-du-conseil-municipal | K81: Vérifié | L81: C | M81: À contacter
A82: 81 | B82: Mairie du Plateau (maire : Jacques Ehouo) | C82: Mairies & acheteurs publics | D82: Abidjan | E82: Plateau | F82: Commune | G82: Chaises, tables | H82: non relevé | I82: Réélu en 2023 | J82: https://www.fratmat.info/article/232388/politique/eacutelections-municipales/municipales-aby-raoul-et-ehouo-jacques-reelus | K82: Vérifié | L82: C | M82: À contacter
A83: 82 | B83: Mairie de Yamoussoukro (maire : Kouassi Kouamé Patrice) | C83: Mairies & acheteurs publics | D83: Intérieur | E83: Yamoussoukro | F83: Commune | G83: Chaises, tables, poubelles | H83: non relevé | I83: Élu le 20/09/2023 | J83: https://www.koaci.com/article/2023/09/21/cote-divoire/politique/cote-divoire-confirme-maire-de-yamoussoukro-par-les-conseillers-municipaux-kkp-tend-la-main-a-ses-adversaires_172430.html | K83: Vérifié | L83: B | M83: À contacter
A84: 83 | B84: Mairie de Bouaké | C84: Mairies & acheteurs publics | D84: Intérieur | E84: Bouaké | F84: Commune | G84: Chaises, tables, poubelles | H84: site mairiedebouake.ci | I84: Nom du maire élu en 2023 à vérifier | J84: https://www.mairiedebouake.ci/ | K84: À vérifier | L84: B | M84: À contacter
A85: 84 | B85: Mairie de Korhogo (maire : Lacina Ouattara) | C85: Mairies & acheteurs publics | D85: Intérieur | E85: Korhogo | F85: Commune | G85: Chaises, tables, cuves | H85: non relevé | I85: Élu en 2023 ; budget 2025 adopté | J85: https://www.aip.ci/cote-divoire-aip-le-conseil-municipal-de-korhogo-adopte-un-budget-primitif-2025-avec-des-projets-innovants/ | K85: Vérifié | L85: B | M85: À contacter
A86: 85 | B86: Mairie de San-Pédro (maire : Mme Cissé née Kéita Nakaridja) | C86: Mairies & acheteurs publics | D86: Intérieur | E86: San-Pédro | F86: Commune | G86: Chaises, tables, poubelles | H86: non relevé | I86: Élue en 2023 | J86: https://www.aip.ci/cote-divoire-aip-keita-epouse-cisse-nakaridja-recoit-les-charges-de-sa-fonction-de-maire-de-san-pedro/ | K86: Vérifié | L86: C | M86: À contacter
... A90: 89 | B90: DGMP, portail des marchés publics (SIGOMAP) | C90: Mairies & acheteurs publics | D90: National | E90: Abidjan | F90: Veille des appels d'offres publics | G90: Mobilier, cuves, fosses | H90: info@marchespublics.gouv.ci ; 27 22 55 88 88 | I90: S'inscrire pour recevoir les appels d'offres « chaises », « tables-bancs », « fosses » | J90: https://marchespublics.ci | K90: Vérifié | L90: A | M90: À contacter

Sheet Zones d'Adjamé
A1: Pôle | B1: Où | C1: Ce qu'on y vend | D1: Produits Taj Plast | E1: Source | F1: Certitude
A2: Boulevard Nangui Abrogoua / route de Roxy | B2: Adjamé, entre la Mosquée et Roxy | C2: Articles ménagers, vaisselle, plastique | D2: Ménage, cuisine, rangement, bidons | E2: https://www.goafricaonline.com/ci/85633-mondial-menage-articles-menagers-abidjan-cote-ivoire | F2: Vérifié (plusieurs fiches)
A3: Pôle Maternité Marie-Thérèse / 220 Logements | B3: Adjamé | C3: Quincaillerie, plomberie, matériaux | D3: Cuves, fosses, tube orange | E3: https://www.goafricaonline.com/ci/annuaire/quincailleries | F3: Vérifié (plusieurs fiches)
A4: Forum des marchés d'Adjamé | B4: Adjamé | C4: Marché de gros multi-produits | D4: Ménage, mobilier | E4: https://mondafrique.com/societe/le-promoteur-du-plus-grand-marche-dafrique-de-louest-floue-par-les-commercants | F4: Vérifié (presse)
A5: Black Market | B5: Adjamé, rue E10, quartier Mirador | C5: Revente, petits commerçants | D5: Ménage, tube orange | E5: https://www.goafricaonline.com/ci/annuaire/quincailleries | F5: À vérifier
A6: Grand marché de Koumassi | B6: Koumassi, à côté de l'usine | C6: Articles en plastique | D6: Toute la gamme ménage | E6: https://www.goafricaonline.com/ci/593835-ok-plast-industrie-plastique-abidjan-cote-ivoire | F6: À vérifier
A8: Aucune association de grossistes en plastique n'a été trouvée en ligne : la liste nominative d'Adjamé se construit sur le terrain, en remplissant l'onglet Cibles au fil de la tournée.

Sheet Méthode et limites
A1: Méthode
A2: Sources : liste officielle des programmes immobiliers agréés (ministère de la Construction, version du 31/08/2026), sites des enseignes (Prosuma, Carrefour, Auchan, CFAO), annuaire Go Africa Online, presse ivoirienne 2023-2026 (Fraternité Matin, AIP, Abidjan.net, Koaci), portail des marchés publics et SangoBids.
A3: Relevé fait le 27/10/2026. Chaque ligne de l'onglet Cibles porte son lien source.
A5: Limites
A6: • Aucun contact acheteur nominatif n'est public pour les chaînes : seul le standard Prosuma l'est. Les acheteurs se trouvent par appel au standard ou sur LinkedIn.
A7: • Les grossistes d'Adjamé n'apparaissent que dans l'annuaire : ils restent « à vérifier » tant qu'un passage ne les a pas confirmés.
A8: • Leader Price : on ne sait pas si l'enseigne existe encore depuis le rachat par CFAO en 2022.
A9: • Plusieurs entreprises de la liste vendent déjà du plastique (Decorplast, OK Plast, KLJ) : revendeur possible ou concurrent, à qualifier.
A10: • Concurrent repéré sur les cuves et fosses : « Tout pour le stockage » (toutpourlestockage-ci.com).
A12: Ce qu'il manque pour aller plus loin
A13: • La liste des revendeurs actuels de Taj Plast, pour retirer les doublons et repérer les villes non couvertes.
A14: • Les produits phares par canal et la grille de prix revendeur, pour adapter l'angle à chaque catégorie.
