Workbook

Sheet Rétroplanning
D1: Dossier de soumission, suivi interne
D2: CONS-PLS-2026-07 (FICTIF), Fourniture et mise en service d'une solution d'encaissement électronique (Mobile Money, cartes, QR code) pour 14 officines du Plateau et de Cocody
A4: Date et heure limites de dépôt | B4: 46332.417 | C4: Recopiée du dossier de consultation. Toutes les dates se recalculent à rebours.
A5: Date du jour | B5: 46311
A6: Jours restants avant le dépôt | B6: =INT(B4)-B5
A8: Jalon | B8: Jours avant le dépôt | C8: Date limite calculée | D8: Responsable | E8: Statut | F8: Point critique | G8: Jours restants
A9: Attestation ou copie de l'agrément de Julaya (établissement de paiement BCEAO) et lettre de partenariat Julaya-Jèko | B9: 15 | C9: =INT($B$4)-B9 | D9: Direction de Jèko | E9: À faire | F9: Oui : pièce détenue par un tiers (Julaya), délai inconnu | G9: =C9-$B$5
A10: Réponse écrite de l'équipe produit sur le fonctionnement sans connexion (exigence 3.4 du cahier des charges FICTIF) | B10: 14 | C10: =INT($B$4)-B10 | D10: Équipe produit Jèko | E10: À faire | F10: Oui : le site se contredit sur ce point | G10: =C10-$B$5
A11: Attestations de régularité fiscale et sociale à jour | B11: 10 | C11: =INT($B$4)-B11 | D11: Administration de Jèko | E11: À faire | F11: Oui si une attestation expire avant le 06/11 | G11: =C11-$B$5
A12: Lettres de référence de 2 commerces clients (accord écrit de citer) | B12: 9 | C12: =INT($B$4)-B12 | D12: Kouassi | E12: À faire | F12: Non | G12: =C12-$B$5
A13: Prix arrêtés et remise éventuelle validés par la direction | B13: 7 | C13: =INT($B$4)-B13 | D13: Direction de Jèko | E13: En cours | F13: Non | G13: =C13-$B$5
A14: Offre technique rédigée (réponse point par point au cahier des charges) | B14: 4 | C14: =INT($B$4)-B14 | D14: Kouassi | E14: En cours | F14: Non | G14: =C14-$B$5
A15: Relecture de conformité du dossier complet contre le cahier des charges | B15: 2 | C15: =INT($B$4)-B15 | D15: Direction commerciale | E15: À faire | F15: Non | G15: =C15-$B$5
A16: Signature, cachet, copies, mise sous pli | B16: 1 | C16: =INT($B$4)-B16 | D16: Administration de Jèko | E16: À faire | F16: Non | G16: =C16-$B$5
A25: Jèko, Abidjan, Côte d'Ivoire · jeko.africa. Document d'entraînement : consultation, acheteur et calendrier FICTIFS.
A26: Document confidentiel, réservé à l'acheteur destinataire.

Sheet Pièces administratives
D1: Pièces administratives
D2: Liste tirée du dossier de consultation, jamais d'un dossier précédent
A5: Pièce exigée | B5: Forme exigée | C5: Validité | D5: Organisme émetteur | E5: Délai d'obtention | F5: Statut | G5: Contrôle au dépôt
A6: Extrait du registre du commerce et du crédit mobilier (RCCM) | B6: Copie certifiée conforme | D6: Tribunal de commerce d'Abidjan | E6: À demander au greffe | F6: À demander | G6: =IF(C6="","Validité à lire sur la pièce",IF(C6<INT(Rétroplanning!$B$4),"EXPIRE AVANT LE DÉPÔT","Valide au dépôt"))
A7: Attestation de régularité fiscale | B7: Original | D7: DGI | E7: À demander à la DGI | F7: À demander | G7: =IF(C7="","Validité à lire sur la pièce",IF(C7<INT(Rétroplanning!$B$4),"EXPIRE AVANT LE DÉPÔT","Valide au dépôt"))
A8: Attestation de mise à jour CNPS | B8: Original | D8: CNPS | E8: À demander à la CNPS | F8: À demander | G8: =IF(C8="","Validité à lire sur la pièce",IF(C8<INT(Rétroplanning!$B$4),"EXPIRE AVANT LE DÉPÔT","Valide au dépôt"))
A9: Justificatif d'agrément de l'établissement de paiement (Julaya) et lettre de partenariat | B9: Copie certifiée conforme | D9: Julaya (agrément BCEAO) | E9: À demander à Julaya | F9: À demander | G9: =IF(C9="","Validité à lire sur la pièce",IF(C9<INT(Rétroplanning!$B$4),"EXPIRE AVANT LE DÉPÔT","Valide au dépôt"))
A10: Attestation de conformité PCI DSS | B10: Copie | D10: Organisme certificateur de Jèko | E10: À demander à l'équipe technique | F10: À demander | G10: =IF(C10="","Validité à lire sur la pièce",IF(C10<INT(Rétroplanning!$B$4),"EXPIRE AVANT LE DÉPÔT","Valide au dépôt"))
A11: Pouvoir du signataire | B11: Original | D11: Jèko (direction générale) | E11: Interne | F11: À demander | G11: =IF(C11="","Validité à lire sur la pièce",IF(C11<INT(Rétroplanning!$B$4),"EXPIRE AVANT LE DÉPÔT","Valide au dépôt"))
A20: Jèko, Abidjan, Côte d'Ivoire · jeko.africa. Document d'entraînement : consultation, acheteur et calendrier FICTIFS.
A21: Document confidentiel, réservé à l'acheteur destinataire.

Sheet Offre financière
D1: Offre financière
D2: Format imposé par le dossier de consultation, montants en FCFA TTC
A5: Poste | B5: Désignation | C5: Unité | D5: Quantité | E5: Prix unitaire | F5: Montant | G5: Source du prix
A6: 1 | B6: Jèko Box, terminal d'encaissement (installation, prise en main, Wifi, mises à jour, assistance 7j/7, garantie 12 mois inclus) | C6: terminal | D6: 22 | E6: 50000 | F6: =IF(ISNUMBER(E6),D6*E6,"") | G6: Tarif public jeko.africa/pricing, 15/10/2026
A7: 2 | B7: Carte SIM avec forfait internet, première année | C7: SIM/an | D7: 22 | E7: 25000 | F7: =IF(ISNUMBER(E7),D7*E7,"") | G7: Tarif public jeko.africa/pricing, 15/10/2026
A8: 3 | B8: Commission sur paiements encaissés en officine : 1 % par transaction réussie (hors montant fixe, non chiffrable à l'avance) | C8: forfait | D8: 1 | E8: 0 | F8: =IF(ISNUMBER(E8),D8*E8,"") | G8: Tarif public jeko.africa/pricing : 1 % en magasin ; transfert vers Wave 1,5 % ; virement 1 000 F
B9: Montant total de l'offre | F9: =SUM(F6:F8)
B10: Contrôle | F10: =IF(COUNTIF(E6:E8,"⟦à renseigner⟧")=0,"Tous les prix sont posés","PRIX MANQUANTS")
A13: Jèko, Abidjan, Côte d'Ivoire · jeko.africa. Document d'entraînement : consultation, acheteur et calendrier FICTIFS.
A14: Document confidentiel, réservé à l'acheteur destinataire.

Sheet Références
D1: Références et capacités
D2: Une référence sans attestation jointe n'existe pas pour la commission
A5: Marché de référence | B5: Client | C5: Objet | D5: Période | E5: Attestation jointe
A6: ⟦Équipement d'un commerce client⟧ | B6: ⟦Client ayant donné son accord écrit⟧ | C6: Jèko Box et encaissement multi-moyens | D6: ⟦à renseigner⟧ | E6: Non
A9: Jèko, Abidjan, Côte d'Ivoire · jeko.africa. Document d'entraînement : consultation, acheteur et calendrier FICTIFS.
A10: Document confidentiel, réservé à l'acheteur destinataire.

Sheet Dépôt et sommaire
D1: Dépôt du pli et sommaire
D2: Recopié mot pour mot du dossier de consultation
A5: Autorité contractante | B5: Groupement Pharmacies Lagune Santé (FICTIF), direction administrative et financière
A6: Lieu de dépôt | B6: Secrétariat de la DAF, contre récépissé, et copie PDF par courriel à l'adresse indiquée au dossier (FICTIF)
A7: Date et heure limites | B7: =Rétroplanning!B4
A8: Exemplaires | B8: Un original et deux copies, sous pli fermé, plus une copie PDF (FICTIF)
A9: Libellé du pli | B9: « Consultation CONS-PLS-2026-07, solution d'encaissement : à n'ouvrir qu'en séance » (FICTIF)
A11: Ordre | B11: Pièce du sommaire
A12: 1 | B12: Lettre de soumission signée
A13: 2 | B13: Pièces administratives (article 5 du dossier FICTIF)
A14: 3 | B14: Présentation du candidat et cadre réglementaire (Julaya)
A15: 4 | B15: Références de commerces équipés
A16: 5 | B16: Offre technique : réponse aux exigences 3.1 à 3.8
A17: 6 | B17: Planning de déploiement sur les 14 officines
A18: 7 | B18: Offre financière : bordereau des prix et conditions de commission
A20: Ce classeur reste interne : il ne fait pas partie du dossier remis.
A22: Jèko, Abidjan, Côte d'Ivoire · jeko.africa. Document d'entraînement : consultation, acheteur et calendrier FICTIFS.
A23: Document confidentiel, réservé à l'acheteur destinataire.
